LICENSE.md
MANIFEST.in
README.rst
setup.py
csvshuf/__init__.py
csvshuf/__main__.py
csvshuf/csvshuf.py
csvshuf.egg-info/PKG-INFO
csvshuf.egg-info/SOURCES.txt
csvshuf.egg-info/dependency_links.txt
csvshuf.egg-info/entry_points.txt
csvshuf.egg-info/top_level.txt